dsf_access_sdk/__init__.py
dsf_access_sdk/client.py
dsf_access_sdk/exceptions.py
dsf_access_sdk/models.py
dsf_access_sdk-1.0.5.dist-info/METADATA
dsf_access_sdk-1.0.5.dist-info/WHEEL
dsf_access_sdk-1.0.5.dist-info/top_level.txt
dsf_access_sdk-1.0.5.dist-info/RECORD
